<?xml version="1.0"?>
<?xml-stylesheet type="text/xsl" href="../PSD_R2x3.xsl"?>
<PropertySetDef><IfcVersion version="2x3 TC1" schema="IfcSharedBldgServiceElements"/><Name>Pset_FlowFittingDuctFitting</Name><Definition>Definition from IAI: Duct fitting occurrence attributes attached to an instance of IfcFlowFitting.
</Definition><Applicability>Entity common property set</Applicability><ApplicableClasses><ClassName>IfcFlowFitting</ClassName></ApplicableClasses><ApplicableTypeValue></ApplicableTypeValue><PropertyDefs><PropertyDef><Name>AbsoluteRoughnessFactor</Name><PropertyType><TypePropertySingleValue><DataType type="IfcPositiveLengthMeasure"/><UnitType type="LENGTHUNIT"/></TypePropertySingleValue></PropertyType><ValueDef/><Definition>The absolute roughness factor of the duct fitting.</Definition></PropertyDef><PropertyDef><Name>HasLiner</Name><PropertyType><TypePropertySingleValue><DataType type="IfcBoolean"/></TypePropertySingleValue></PropertyType><ValueDef/><Definition>TRUE if the fitting has interior duct insulating lining, FALSE if it does not.</Definition></PropertyDef><PropertyDef><Name>Color</Name><PropertyType><TypePropertySingleValue><DataType type="IfcLabel"/></TypePropertySingleValue></PropertyType><ValueDef/><Definition>The color of the duct fitting.

Note: This is typically used for any duct fittings with a painted surface which is not otherwise specified as a covering.</Definition></PropertyDef></PropertyDefs></PropertySetDef>
